git_conflict_daemon.py
git_conflict_daemon-0.1.0.dist-info/METADATA
git_conflict_daemon-0.1.0.dist-info/WHEEL
git_conflict_daemon-0.1.0.dist-info/entry_points.txt
git_conflict_daemon-0.1.0.dist-info/top_level.txt
git_conflict_daemon-0.1.0.dist-info/RECORD
